slambda/__init__.py
slambda/core.py
slambda/gpt.py
slambda/utils.py
slambda/contrib/__init__.py
slambda/contrib/entail.py
slambda/contrib/motivate.py
slambda/contrib/sentiment.py
slambda/contrib/summarize.py
slambda/contrib/wiki_link.py
slambda/contrib/writing/__init__.py
slambda/contrib/writing/essay.py
slambda/contrib/writing/grammar.py
slambda-0.0.15.dist-info/METADATA
slambda-0.0.15.dist-info/WHEEL
slambda-0.0.15.dist-info/licenses/LICENSE
slambda-0.0.15.dist-info/RECORD
