Metadata-Version: 2.3
Name: slambda
Version: 0.0.15
Summary: Instruction is Function!
Project-URL: Homepage, https://slambda.dataset.sh
Project-URL: Bug Tracker, https://github.com/dataset-sh/slambda/issues
Author-email: Hao Wu <haowu@dataset.sh>
License: MIT License
License-File: LICENSE
Classifier: License :: OSI Approved :: MIT License
Classifier: Operating System :: OS Independent
Classifier: Programming Language :: Python :: 3
Classifier: Topic :: Scientific/Engineering :: Artificial Intelligence
Classifier: Topic :: Scientific/Engineering :: Information Analysis
Requires-Python: >=3.9
Requires-Dist: cmfn~=0.0.2
Requires-Dist: openai
Requires-Dist: pydantic<3.0.0,>=2.0.0
